encore_bigdata2-0.1.1.dist-info/METADATA
encore_bigdata2-0.1.1.dist-info/WHEEL
encore_bigdata2-0.1.1.dist-info/entry_points.txt
encore_bigdata2/__init__.py
encore_bigdata2/app_8trider.py
encore_bigdata2/app_doxgxxn.py
encore_bigdata2/app_felicette.py
encore_bigdata2/app_jiug.py
encore_bigdata2/app_tjkpolisher.py
encore_bigdata2-0.1.1.dist-info/RECORD
