Metadata-Version: 2.1
Name: encore_bigdata2
Version: 0.1.1
Author-Email: 8trider <8trider@naver.com>, jiughan <wldnd4081@gmail.com>
License: MIT
Project-URL: Homepage, https://github.com/DJMLteam2/encore_bigdata2
Project-URL: Bug tracker, https://github.com/DJMLteam2/encore_bigdata2/issues
Requires-Python: >=3.8
